planajobv6.py
planajob-6.1.2.dist-info/LICENSE
planajob-6.1.2.dist-info/METADATA
planajob-6.1.2.dist-info/WHEEL
planajob-6.1.2.dist-info/top_level.txt
planajob-6.1.2.dist-info/RECORD
