Metadata-Version: 2.1
Name: planajob
Version: 6.1.2
Summary: A sales order and purchasing package, version 5.1.2 corrects a bug
Home-page: UNKNOWN
Author: Terry Hughes
Author-email: terryhugheskirkcudbright@yahoo.co.uk
License: UNKNOWN
Platform: UNKNOWN
Classifier: Programming Language :: Python :: 3
Classifier: License :: OSI Approved :: MIT License
Classifier: Operating System :: OS Independent
Requires-Python: >=3.6
